revealjs/__init__.py
revealjs/interface.py
revealjs/reveal_js.py
revealjs-0.2.10.data/data/revealjs/slide.adoc
revealjs-0.2.10.dist-info/METADATA
revealjs-0.2.10.dist-info/WHEEL
revealjs-0.2.10.dist-info/entry_points.txt
revealjs-0.2.10.dist-info/top_level.txt
revealjs-0.2.10.dist-info/RECORD
