Metadata-Version: 2.1
Name: revealjs
Version: 0.2.10
Summary: Reveal.js Presentation Builder Inspired By revealjs
Home-page: https://github.com/gunaNeelamegam/revealjs-presentation.git
Author: guna
Author-email: gunag5127@gmail.com
License: UNKNOWN
Platform: UNKNOWN
Requires-Dist: bs4
Requires-Dist: inquirer
Requires-Dist: requests
